LICENSE.txt
MANIFEST.in
README.md
setup.py
fixed_select_version_PyVirtualDisplay.egg-info/PKG-INFO
fixed_select_version_PyVirtualDisplay.egg-info/SOURCES.txt
fixed_select_version_PyVirtualDisplay.egg-info/dependency_links.txt
fixed_select_version_PyVirtualDisplay.egg-info/top_level.txt
pyvirtualdisplay/__init__.py
pyvirtualdisplay/about.py
pyvirtualdisplay/abstractdisplay.py
pyvirtualdisplay/display.py
pyvirtualdisplay/py.typed
pyvirtualdisplay/smartdisplay.py
pyvirtualdisplay/util.py
pyvirtualdisplay/xauth.py
pyvirtualdisplay/xephyr.py
pyvirtualdisplay/xvfb.py
pyvirtualdisplay/xvnc.py
pyvirtualdisplay/examples/__init__.py
pyvirtualdisplay/examples/headless.py
pyvirtualdisplay/examples/lowres.py
pyvirtualdisplay/examples/nested.py
pyvirtualdisplay/examples/screenshot.py
pyvirtualdisplay/examples/threadsafe.py
pyvirtualdisplay/examples/vncserver.py
tests/slowgui.py
tests/test_core.py
tests/test_examples.py
tests/test_race.py
tests/test_smart.py
tests/test_smart2.py
tests/test_smart_thread.py
tests/test_threads.py
tests/test_with.py
tests/test_xauth.py
tests/test_xvnc.py
tests/tutil.py
tests/vagrant/vagrant_boxes.py